Metadata-Version: 1.1
Name: sjcl
Version: 0.1.3
Summary: 
